climdex/__init__.py
climdex/__main__.py
climdex/_version.py
climdex/cli.py
climdex/climdex-imports
climdex/cmodels.py
climdex/constants.py
climdex/indices.py
climdex/nc.py
climdex/utils.py
climdex/actions/__init__.py
climdex/actions/analyse.py
climdex/actions/compute.py
climdex/actions/list.py
climdex/actions/mlut.py
climdex/actions/show.py
climdex/analyse/__init__.py
climdex/analyse/enums.py
climdex/analyse/filesystem.py
climdex/analyse/maps.py
climdex/analyse/maps_nc.py
climdex/analyse/plots.py
climdex/analyse/trends.py
climdex/analyse/trends_nc.py
climdex/analyse/utils.py
climdex/analyse/xarrays.py
climdex/bindings/cdobnd.py
climdex/bindings/cibnd.py
climdex/etc/indices.ini
climdex/etc/logging.yaml
climdex/etc/models_lut.json
climdex/workers/cdowrk.py
climdex/workers/ciwrk.py
climdex/workers/iworker.py
climdex/workers/registry.py
climdex_kit-1.0.1.dist-info/AUTHORS
climdex_kit-1.0.1.dist-info/LICENSE
climdex_kit-1.0.1.dist-info/METADATA
climdex_kit-1.0.1.dist-info/WHEEL
climdex_kit-1.0.1.dist-info/entry_points.txt
climdex_kit-1.0.1.dist-info/top_level.txt
climdex_kit-1.0.1.dist-info/RECORD
