Metadata-Version: 2.1
Name: climdex-kit
Version: 1.0.1
Summary: Tool for multi-scenario calculation, publishing, and analysis of indices from 3D time-series of climate projections.
Home-page: https://gitlab.inf.unibz.it/earth_observation_public/cdr/climdex-kit
Download-URL: https://gitlab.inf.unibz.it/earth_observation_public/cdr/climdex-kit/-/releases/v1.0.1
Author: Piero Campalani
Author-email: piero.campalani@eurac.edu
Maintainer: Piero Campalani
Maintainer-email: piero.campalani@eurac.edu
Project-URL: Bug Tracker, https://gitlab.inf.unibz.it/earth_observation_public/cdr/climdex-kit/-/issues
Project-URL: Source, https://gitlab.inf.unibz.it/earth_observation_public/cdr/climdex-kit
Keywords: indices,climate,scenario
Classifier: Programming Language :: Python :: 3
Classifier: Programming Language :: Python :: 3.8
Classifier: Programming Language :: Python :: 3.9
Classifier: Programming Language :: Python :: 3.10
Classifier: Programming Language :: Python :: 3.11
Classifier: Programming Language :: Python :: 3.12
Classifier: License :: OSI Approved :: GNU General Public License v3 (GPLv3)
Classifier: Operating System :: OS Independent
Classifier: Development Status :: 4 - Beta
Classifier: Intended Audience :: Developers
Classifier: Intended Audience :: Education
Classifier: Intended Audience :: Science/Research
Classifier: Topic :: Software Development :: Libraries :: Python Modules
Classifier: Topic :: Scientific/Engineering :: Atmospheric Science
Classifier: Topic :: Scientific/Engineering :: Physics
Requires-Python: >=3.8
License-File: LICENSE
License-File: AUTHORS
Requires-Dist: cdo
Requires-Dist: climate-indices
Requires-Dist: geopandas
Requires-Dist: importlib-resources
Requires-Dist: netcdf4
Requires-Dist: nco
Requires-Dist: rioxarray
Requires-Dist: shapely
Provides-Extra: interactive
Requires-Dist: jupyter; extra == "interactive"
Requires-Dist: matplotlib; extra == "interactive"
Provides-Extra: tests
Requires-Dist: ddt; extra == "tests"
Provides-Extra: docs
